rezparser/__init__.py
rezparser/_table_parser_expr.py
rezparser/_table_parser_file.py
rezparser/ast.py
rezparser/common.py
rezparser/eval.py
rezparser/lexer.py
rezparser/parser.py
rezparser/parser_retro68.py
rezparser/preprocessor.py
rezparser-1.0.0.dist-info/DESCRIPTION.rst
rezparser-1.0.0.dist-info/METADATA
rezparser-1.0.0.dist-info/RECORD
rezparser-1.0.0.dist-info/WHEEL
rezparser-1.0.0.dist-info/metadata.json
rezparser-1.0.0.dist-info/top_level.txt
