Metadata-Version: 2.0
Name: rezparser
Version: 1.0.0
Summary: A pure Python library for parsing Macintosh Rez source files
Home-page: https://github.com/dgelessus/python-rezparser
Author: dgelessus
Author-email: UNKNOWN
License: MIT
Keywords: rez resource macintosh mac macos
Platform: UNKNOWN
Classifier: Development Status :: 4 - Beta
Classifier: Intended Audience :: Developers
Classifier: Topic :: Software Development :: Libraries :: Python Modules
Classifier: Topic :: Utilities
Classifier: License :: OSI Approved :: MIT License
Classifier: Operating System :: OS Independent
Classifier: Programming Language :: Python
Classifier: Programming Language :: Python :: 3
Classifier: Programming Language :: Python :: 3 :: Only
Classifier: Programming Language :: Python :: 3.6
Requires-Python: >=3.6
Requires-Dist: ply
